LICENSE
MANIFEST.in
README.rst
runtests.py
setup.py
django_synchro.egg-info/PKG-INFO
django_synchro.egg-info/SOURCES.txt
django_synchro.egg-info/dependency_links.txt
django_synchro.egg-info/requires.txt
django_synchro.egg-info/top_level.txt
synchro/__init__.py
synchro/apps.py
synchro/core.py
synchro/handlers.py
synchro/models.py
synchro/settings.py
synchro/signals.py
synchro/test_urls.py
synchro/tests.py
synchro/urls.py
synchro/utility.py
synchro/views.py
synchro/locale/de/LC_MESSAGES/django.mo
synchro/locale/de/LC_MESSAGES/django.po
synchro/locale/es/LC_MESSAGES/django.mo
synchro/locale/es/LC_MESSAGES/django.po
synchro/locale/fr/LC_MESSAGES/django.mo
synchro/locale/fr/LC_MESSAGES/django.po
synchro/locale/pl/LC_MESSAGES/django.mo
synchro/locale/pl/LC_MESSAGES/django.po
synchro/management/__init__.py
synchro/management/commands/__init__.py
synchro/management/commands/synchronize.py
synchro/templates/synchro.html