Metadata-Version: 1.1
Name: django-synchro
Version: 0.7
Summary: Django app for database data synchronization.
Home-page: https://github.com/zlorf/django-synchro
Author: Jacek Tomaszewski
Author-email: jacek.tomek@gmail.com
License: MIT
Platform: UNKNOWN
Classifier: Development Status :: 4 - Beta
Classifier: Environment :: Web Environment
Classifier: License :: OSI Approved :: MIT License
Classifier: Operating System :: OS Independent
Classifier: Programming Language :: Python
Classifier: Framework :: Django
Classifier: Framework :: Django :: 1.7
Classifier: Framework :: Django :: 1.8
Classifier: Framework :: Django :: 1.9
Classifier: Framework :: Django :: 1.10
Classifier: Framework :: Django :: 1.11
